llaminate/.old/models.py
llaminate/__init__.py
llaminate/layers.py
llaminate/meta.py
llaminate/models.py
llaminate/pipeline.py
llaminate/utils.py
llaminate-0.7.4.dist-info/METADATA
llaminate-0.7.4.dist-info/WHEEL
llaminate-0.7.4.dist-info/RECORD
