Metadata-Version: 2.3
Name: llaminate
Version: 0.7.4
Summary: Optimized version of llama3 / gemma.
Author: apehex
Author-email: apehex@protonmail.com
Requires-Python: >=3.10,<3.13
Classifier: Programming Language :: Python :: 3
Classifier: Programming Language :: Python :: 3.10
Classifier: Programming Language :: Python :: 3.11
Classifier: Programming Language :: Python :: 3.12
Requires-Dist: mlable (>=0.20)
Requires-Dist: tensorflow (>=2.16,<2.20)
